embedsrt/__init__.py
embedsrt-0.0.4.dist-info/METADATA
embedsrt-0.0.4.dist-info/WHEEL
embedsrt-0.0.4.dist-info/entry_points.txt
embedsrt-0.0.4.dist-info/top_level.txt
embedsrt-0.0.4.dist-info/RECORD
