Metadata-Version: 2.1
Name: embedsrt
Version: 0.0.4
Summary: a utility for embedding subtitle file into video file
Home-page: https://github.com/botbahlul/embedsrt
Author: Bot Bahlul
Author-email: bot.bahlul@gmail.com
License: MIT License
Requires-Dist: pysrt (>=1.0.1)
Requires-Dist: progressbar2 (>=3.34.3)
